schubmult/__init__.py
schubmult/perm_lib.py
schubmult/poly_lib/__init__.py
schubmult/poly_lib/poly_lib.py
schubmult/poly_lib/schub_poly.py
schubmult/poly_lib/variables.py
schubmult/rings/__init__.py
schubmult/rings/_quantum_schubert_polynomial_ring.py
schubmult/rings/_schubert_polynomial_ring.py
schubmult/rings/_tensor_schub_ring.py
schubmult/rings/_utils.py
schubmult/sage/__init__.py
schubmult/sage/_fast_double_schubert_polynomial_ring.py
schubmult/sage/_fast_schubert_polynomial_ring.py
schubmult/sage/_indexing.py
schubmult/schub_lib/__init__.py
schubmult/schub_lib/double.py
schubmult/schub_lib/quantum.py
schubmult/schub_lib/quantum_double.py
schubmult/schub_lib/schub_lib.py
schubmult/schub_lib/single.py
schubmult/schub_lib/tests/__init__.py
schubmult/schub_lib/tests/legacy_perm_lib.py
schubmult/schub_lib/tests/test_vs_old.py
schubmult/scripts/__init__.py
schubmult/scripts/schubmult_double.py
schubmult/scripts/schubmult_py.py
schubmult/scripts/schubmult_q.py
schubmult/scripts/schubmult_q_double.py
schubmult/utils/__init__.py
schubmult/utils/argparse.py
schubmult/utils/logging.py
schubmult/utils/parsing.py
schubmult/utils/perm_utils.py
schubmult/utils/test_utils.py
schubmult-3.0.1.dist-info/licenses/LICENSE
schubmult-3.0.1.dist-info/METADATA
schubmult-3.0.1.dist-info/WHEEL
schubmult-3.0.1.dist-info/entry_points.txt
schubmult-3.0.1.dist-info/top_level.txt
schubmult-3.0.1.dist-info/RECORD
