Metadata-Version: 2.4
Name: schubmult
Version: 3.0.1
Summary: Package for algebraic computation with single, double, and quantum Schubert polynomials
Author-email: Matt Samuel <schubmult@gmail.com>
Maintainer-email: Matt Samuel <schubmult@gmail.com>
License:                     GNU GENERAL PUBLIC LICENSE
Project-URL: Homepage, http://schubmult.org
Project-URL: Repository, https://github.com/matthematics/schubmult
Keywords: Schubert,polynomial,double,algebra
Classifier: Programming Language :: Python
Requires-Python: >=3.9
License-File: LICENSE
Requires-Dist: numpy
Requires-Dist: PuLP>=2.7.0
Requires-Dist: symengine>=0.14.0
Requires-Dist: sympy>=1.13.3
Requires-Dist: psutil
Requires-Dist: cachetools
Requires-Dist: sortedcontainers
Requires-Dist: setuptools
Provides-Extra: sage
Requires-Dist: sagemath-standard; extra == "sage"
Dynamic: license-file
